MANIFEST.in
README.rst
setup.py
aliyun_python_sdk_cs.egg-info/PKG-INFO
aliyun_python_sdk_cs.egg-info/SOURCES.txt
aliyun_python_sdk_cs.egg-info/dependency_links.txt
aliyun_python_sdk_cs.egg-info/requires.txt
aliyun_python_sdk_cs.egg-info/top_level.txt
aliyunsdkcs/__init__.py
aliyunsdkcs/endpoint.py
aliyunsdkcs/request/__init__.py
aliyunsdkcs/request/v20151215/AttachInstancesRequest.py
aliyunsdkcs/request/v20151215/CancelClusterUpgradeRequest.py
aliyunsdkcs/request/v20151215/CancelComponentUpgradeRequest.py
aliyunsdkcs/request/v20151215/CancelWorkflowRequest.py
aliyunsdkcs/request/v20151215/CreateClusterRequest.py
aliyunsdkcs/request/v20151215/CreateKubernetesTriggerRequest.py
aliyunsdkcs/request/v20151215/CreateTemplateRequest.py
aliyunsdkcs/request/v20151215/DeleteClusterNodesRequest.py
aliyunsdkcs/request/v20151215/DeleteClusterRequest.py
aliyunsdkcs/request/v20151215/DeleteKubernetesTriggerRequest.py
aliyunsdkcs/request/v20151215/DeleteTemplateRequest.py
aliyunsdkcs/request/v20151215/DescirbeWorkflowRequest.py
aliyunsdkcs/request/v20151215/DescribeAddonsRequest.py
aliyunsdkcs/request/v20151215/DescribeClusterAddonUpgradeStatusRequest.py
aliyunsdkcs/request/v20151215/DescribeClusterAddonsUpgradeStatusRequest.py
aliyunsdkcs/request/v20151215/DescribeClusterAddonsVersionRequest.py
aliyunsdkcs/request/v20151215/DescribeClusterAttachScriptsRequest.py
aliyunsdkcs/request/v20151215/DescribeClusterDetailRequest.py
aliyunsdkcs/request/v20151215/DescribeClusterLogsRequest.py
aliyunsdkcs/request/v20151215/DescribeClusterNodesRequest.py
aliyunsdkcs/request/v20151215/DescribeClusterResourcesRequest.py
aliyunsdkcs/request/v20151215/DescribeClusterUserKubeconfigRequest.py
aliyunsdkcs/request/v20151215/DescribeClusterV2UserKubeconfigRequest.py
aliyunsdkcs/request/v20151215/DescribeClustersRequest.py
aliyunsdkcs/request/v20151215/DescribeClustersV1Request.py
aliyunsdkcs/request/v20151215/DescribeExternalAgentRequest.py
aliyunsdkcs/request/v20151215/DescribeTemplatesRequest.py
aliyunsdkcs/request/v20151215/DescribeUserQuotaRequest.py
aliyunsdkcs/request/v20151215/DescribeWorkflowsRequest.py
aliyunsdkcs/request/v20151215/GetKubernetesTriggerRequest.py
